dark/__init__.py
dark/decoder.py
dark/modules.py
dark/pid_modules.py
dark/gateway/__init__.py
dark/gateway/core.py
dark/util/__init__.py
dark/util/core_bc_libs.py
dark/util/libs.py
dark/util/setup.py
dark_gateway-1.5.dist-info/LICENSE
dark_gateway-1.5.dist-info/METADATA
dark_gateway-1.5.dist-info/WHEEL
dark_gateway-1.5.dist-info/top_level.txt
dark_gateway-1.5.dist-info/RECORD
